Metadata-Version: 2.2
Name: ConversationalSpaceMapApp
Version: 0.1.2
Summary: Generate conversational space maps for interview data.
Author-email: Manuel Bieri <mail@manuelbieri.ch>
Maintainer-email: Manuel Bieri <mail@manuelbieri.ch>
License: BSD-3-Clause License
Project-URL: Homepage, https://github.com/manuelbieri/ConversationalSpaceMap
Project-URL: Documentation, https://github.com/manuelbieri/ConversationalSpaceMap
Project-URL: Repository, https://github.com/manuelbieri/ConversationalSpaceMapApp.git
Classifier: Development Status :: 4 - Beta
Classifier: Programming Language :: Python :: 3
Classifier: Programming Language :: Python :: 3.12
Classifier: Programming Language :: Python :: 3.13
Requires-Python: >=3.12
License-File: LICENSE
Requires-Dist: toga-chart
Requires-Dist: toga
Requires-Dist: mockito
